ItsuBot/__init__.py
ItsuBot-4.5.8.dist-info/METADATA
ItsuBot-4.5.8.dist-info/WHEEL
ItsuBot-4.5.8.dist-info/top_level.txt
ItsuBot-4.5.8.dist-info/RECORD
