Metadata-Version: 2.1
Name: ItsuBot
Version: 4.5.8
Summary: BOT FORTNITE
Home-page: UNKNOWN
Author: Itsu
Author-email: votre-email@example.com
License: UNKNOWN
Platform: UNKNOWN
Classifier: Programming Language :: Python :: 3
Classifier: License :: OSI Approved :: MIT License
Classifier: Operating System :: OS Independent
